<?xml version="1.0" encoding="utf-8"?>
<users>
  <adresse>
    <Firstname>Test</Firstname>
    <Lastname>test</Lastname>
    <E-Mail>Test</E-Mail>
    <Phonenumber>test</Phonenumber>
    <Street>TEst</Street>
    <House-Number>test</House-Number>
    <Postcode>tEst</Postcode>
    <City>testeter</City>
  </adresse>
  <adresse>
    <Firstname>TEtsft</Firstname>
    <Lastname>TEst</Lastname>
    <E-Mail>testadf@tste.de</E-Mail>
    <Phonenumber>TEast</Phonenumber>
    <Street>Test</Street>
    <House-Number>TEsta</House-Number>
    <Postcode>t231</Postcode>
    <City>TEDstafasf</City>
  </adresse>
    <adresse>
    <Firstname>TEtsft</Firstname>
    <Lastname>TEst</Lastname>
    <E-Mail>testadf@tste.de</E-Mail>
    <Phonenumber>TEast</Phonenumber>
    <Street>Test</Street>
    <House-Number>TEsta</House-Number>
    <Postcode>t231</Postcode>
    <City>TEDstafasf</City>
  </adresse>
    <adresse>
    <Firstname>TEtsft</Firstname>
    <Lastname>TEst</Lastname>
    <E-Mail>testadf@tste.de</E-Mail>
    <Phonenumber>TEast</Phonenumber>
    <Street>Test</Street>
    <House-Number>TEsta</House-Number>
    <Postcode>t231</Postcode>
    <City>TEDstafasf</City>
  </adresse>
    <adresse>
    <Firstname>TEtsft</Firstname>
    <Lastname>TEst</Lastname>
    <E-Mail>testadf@tste.de</E-Mail>
    <Phonenumber>TEast</Phonenumber>
    <Street>Test</Street>
    <House-Number>TEsta</House-Number>
    <Postcode>t231</Postcode>
    <City>TEDstafasf</City>
  </adresse>
    <adresse>
    <Firstname>TEtsft</Firstname>
    <Lastname>TEst</Lastname>
    <E-Mail>testadf@tste.de</E-Mail>
    <Phonenumber>TEast</Phonenumber>
    <Street>Test</Street>
    <House-Number>TEsta</House-Number>
    <Postcode>t231</Postcode>
    <City>TEDstafasf</City>
  </adresse>
    <adresse>
    <Firstname>TEtsft</Firstname>
    <Lastname>TEst</Lastname>
    <E-Mail>testadf@tste.de</E-Mail>
    <Phonenumber>TEast</Phonenumber>
    <Street>Test</Street>
    <House-Number>TEsta</House-Number>
    <Postcode>t231</Postcode>
    <City>TEDstafasf</City>
  </adresse>
    <adresse>
    <Firstname>TEtsft</Firstname>
    <Lastname>TEst</Lastname>
    <E-Mail>testadf@tste.de</E-Mail>
    <Phonenumber>TEast</Phonenumber>
    <Street>Test</Street>
    <House-Number>TEsta</House-Number>
    <Postcode>t231</Postcode>
    <City>TEDstafasf</City>
  </adresse>
    <adresse>
    <Firstname>TEtsft</Firstname>
    <Lastname>TEst</Lastname>
    <E-Mail>testadf@tste.de</E-Mail>
    <Phonenumber>TEast</Phonenumber>
    <Street>Test</Street>
    <House-Number>TEsta</House-Number>
    <Postcode>t231</Postcode>
    <City>TEDstafasf</City>
  </adresse>
    <adresse>
    <Firstname>TEtsft</Firstname>
    <Lastname>TEst</Lastname>
    <E-Mail>testadf@tste.de</E-Mail>
    <Phonenumber>TEast</Phonenumber>
    <Street>Test</Street>
    <House-Number>TEsta</House-Number>
    <Postcode>t231</Postcode>
    <City>TEDstafasf</City>
  </adresse>
    <adresse>
    <Firstname>TEtsft</Firstname>
    <Lastname>TEst</Lastname>
    <E-Mail>testadf@tste.de</E-Mail>
    <Phonenumber>TEast</Phonenumber>
    <Street>Test</Street>
    <House-Number>TEsta</House-Number>
    <Postcode>t231</Postcode>
    <City>TEDstafasf</City>
  </adresse>
    <adresse>
    <Firstname>TEtsft</Firstname>
    <Lastname>TEst</Lastname>
    <E-Mail>testadf@tste.de</E-Mail>
    <Phonenumber>TEast</Phonenumber>
    <Street>Test</Street>
    <House-Number>TEsta</House-Number>
    <Postcode>t231</Postcode>
    <City>TEDstafasf</City>
  </adresse>
</users>